pyportfoliotracker/__init__.py
pyportfoliotracker/objects.py
pyportfoliotracker-0.1.0.dist-info/LICENSE
pyportfoliotracker-0.1.0.dist-info/METADATA
pyportfoliotracker-0.1.0.dist-info/WHEEL
pyportfoliotracker-0.1.0.dist-info/top_level.txt
pyportfoliotracker-0.1.0.dist-info/RECORD
