Metadata-Version: 2.1
Name: pyportfoliotracker
Version: 0.1.0
Summary: Track the performance of your portfolio of equities vs an index
Home-page: https://github.com/bryan-teng/portfolio-tracker
Author: Bryan Teng
Author-email: teng.weiyan.bryan@gmail.com
License: UNKNOWN
Platform: UNKNOWN
Classifier: Programming Language :: Python :: 3
Classifier: License :: OSI Approved :: MIT License
Classifier: Operating System :: OS Independent
Requires-Python: >=3.6
